mappyfile_colors.py
mappyfile_colors-1.0.0.dist-info/LICENSE
mappyfile_colors-1.0.0.dist-info/METADATA
mappyfile_colors-1.0.0.dist-info/WHEEL
mappyfile_colors-1.0.0.dist-info/entry_points.txt
mappyfile_colors-1.0.0.dist-info/top_level.txt
mappyfile_colors-1.0.0.dist-info/RECORD
