Metadata-Version: 2.1
Name: mappyfile-colors
Version: 1.0.0
Summary: A mappyfile plugin to convert between RGB and Hex colors, and to add human readable names
Home-page: http://github.com/geographika/mappyfile-colors
Author: Seth Girvin
Author-email: sethg@geographika.co.uk
License: MIT
Classifier: Development Status :: 5 - Production/Stable
Classifier: License :: OSI Approved :: MIT License
Classifier: Programming Language :: Python :: 3.8
Classifier: Programming Language :: Python :: 3.9
Classifier: Programming Language :: Python :: 3.10
Classifier: Programming Language :: Python :: 3.11
Classifier: Intended Audience :: Developers
Classifier: Topic :: Software Development :: Build Tools
License-File: LICENSE
Requires-Dist: mappyfile >=1.0.2
Requires-Dist: webcolors
